data_elements/authentication_credentials.json
data_elements/communication_behavioral_data.json
data_elements/contact_information.json
data_elements/content_consumption_media_data.json
data_elements/credit_risk_assessment_data.json
data_elements/device_technology_data.json
data_elements/digital_online_identifiers.json
data_elements/ecommerce_shopping_data.json
data_elements/educational_academic_data.json
data_elements/employment_professional_data.json
data_elements/financial_payment_data.json
data_elements/gaming_entertainment_specific_data.json
data_elements/government_issued_identifiers.json
data_elements/health_biometric_data.json
data_elements/insurance_protection_data.json
data_elements/investment_trading_data.json
data_elements/legal_compliance_data.json
data_elements/location_geospatial_data.json
data_elements/logistics_delivery_data.json
data_elements/marketing_analytics_data.json
data_elements/matrimonial_dating_specific_data.json
data_elements/personal_identifiable_information_pii.json
data_elements/preferences_settings_data.json
data_elements/sensitive_personal_data.json
data_elements/service_booking_data.json
data_elements/social_relationship_data.json
data_elements/subscription_membership_data.json
data_elements/technical_system_data.json
data_elements/vendor_merchant_data.json
src/__init__.py
src/ai_scanner.py
src/main.py
src/regex_scanner.py
src/report_utils.py
src/scanner.py
src/utils.py
truscanner-0.2.4.dist-info/METADATA
truscanner-0.2.4.dist-info/WHEEL
truscanner-0.2.4.dist-info/entry_points.txt
truscanner-0.2.4.dist-info/licenses/LICENSE
truscanner-0.2.4.dist-info/RECORD
