Metadata-Version: 2.4
Name: truscanner
Version: 0.2.4
Summary: Open-Source Static Analysis for Privacy Data Flows
Author-email: truconsent <hello@truconsent.io>
License: MIT
License-File: LICENSE
Requires-Python: >=3.9
Requires-Dist: click>=8.1.8
Requires-Dist: inquirer>=3.1.0
Requires-Dist: ollama>=0.1.0
Requires-Dist: openai>=1.0.0
Requires-Dist: python-dotenv>=1.0.0
Requires-Dist: requests>=2.31.0
Provides-Extra: dev
Requires-Dist: build; extra == 'dev'
Requires-Dist: hatchling; extra == 'dev'
Requires-Dist: twine; extra == 'dev'
